README.rst
setup.py
pycodequality/__init__.py
pycodequality.egg-info/PKG-INFO
pycodequality.egg-info/SOURCES.txt
pycodequality.egg-info/dependency_links.txt
pycodequality.egg-info/entry_points.txt
pycodequality.egg-info/requires.txt
pycodequality.egg-info/top_level.txt
pycodequality.egg-info/zip-safe